{
  "items": [
    {
      "id": 1,
      "name": "table",
      "img": "https://picsum.photos/200?random=1"
    },
    {
      "id": 2,
      "name": "chair",
      "img": "https://picsum.photos/200?random=2"
    },
    {
      "id": 3,
      "name": "magazine",
      "img": "https://picsum.photos/200?random=3"
    },
    {
      "id": 4,
      "name": "train",
      "img": "https://picsum.photos/200?random=4"
    },
    {
      "id": 5,
      "name": "shaker",
      "img": "https://picsum.photos/200?random=5"
    },
    {
      "id": 6,
      "name": "gym",
      "img": "https://picsum.photos/200?random=6"
    },
    {
      "id": 7,
      "name": "bus",
      "img": "https://picsum.photos/200?random=7"
    },
    {
      "id": 8,
      "name": "ferrari",
      "img": "https://picsum.photos/200?random=8"
    }
  ],
  "income": [
    {
      "id": 1,
      "data": [
        18000,
        8000,
        20000,
        48200,
        22000,
        10000,
        20000,
        15000,
        37000,
        55000,
        12000,
        18000
      ]
    },
    {
      "id": 2,
      "data": [
        13000,
        8000,
        40000,
        24100,
        16000,
        16000,
        18000,
        8000,
        20000,
        48200,
        22000,
        10000
      ]
    }
  ],
  "cards": [
    {
      "cardName": "VISA CARD",
      "cardType": "VISA",
      "accountNumber": "GE32TB1111222233334444",
      "cardNumber": "4111222233331234",
      "cardholder": "BARRY ARMSTRONG",
      "expirationDate": "10/24",
      "availableAmount": 2000,
      "security3D": false,
      "userId": "3",
      "id": 1,
      "iconPath": "./assets/create-card/create-card-visa-icon.svg"
    },
    {
      "cardName": "MASTER CARD",
      "cardType": "MASTERCARD",
      "accountNumber": "GE32TB2222111133334444",
      "cardNumber": "5222111133338040",
      "cardholder": "JOHN LENNON",
      "expirationDate": "04/30",
      "availableAmount": 25000,
      "security3D": true,
      "userId": "1",
      "id": 2,
      "iconPath": "./assets/create-card/mastercard.svg"
    },
    {
      "cardName": "MASTER CARD",
      "cardType": "MASTERCARD",
      "accountNumber": "GE32TB3333111122224444",
      "cardNumber": "5333111122220097",
      "cardholder": "TILL LINDEMANN",
      "expirationDate": "11/26",
      "availableAmount": 45000,
      "security3D": true,
      "userId": "2",
      "id": 3,
      "iconPath": "./assets/create-card/mastercard.svg"
    }
  ],
  "users": [
    {
      "fullname": "SANCHO PANZA",
      "email": "sanchito_p@gmail.com",
      "password": "12345678",
      "id": 1
    },
    {
      "fullname": "EDMOND DANTES",
      "email": "admin@gmail.com",
      "password": "12345678",
      "id": 2
    },
    {
      "fullname": "VITO CORLEONE",
      "email": "mafia_immortal@outlook.com",
      "password": "ssssssssss",
      "id": 3
    }
  ],
  "deposits": [
    {
      "id": 1,
      "depositName": "Cumulative deposit",
      "accountNumber": "UK64CT00000000000010034567",
      "depositRate": 0.05,
      "startDate": "20.06.2018",
      "expirationDate": "20.06.2022",
      "availableAmount": 56400,
      "accuredInterest": 1640,
      "balance": 56400,
      "accured": 640,
      "type": "Cumulative"
    }
  ],
  "loans": [
    {
      "id": 1,
      "loanName": "Mortgage loan",
      "accountNumber": "UK64CT00000000000010034567",
      "loanRate": 0.14,
      "startDate": "20.06.2018",
      "expirationDate": "20.06.2022",
      "balance": 84800,
      "paid": 24800,
      "blocked": true,
      "type": "Mortgage"
    },
    {
      "id": 2,
      "loanName": "Consumer loan",
      "accountNumber": "UK64CT00000000000010035931",
      "loanRate": 0.18,
      "startDate": "20.06.2018",
      "expirationDate": "20.06.2022",
      "balance": 66400,
      "paid": 650,
      "blocked": false,
      "type": "Consumer"
    }
  ],
  "charts": [
    {
      "id": 1,
      "name": "Cards balance",
      "data": [78000, 91000, 78000, 52000, 72800, 104000, 124800]
    },
    {
      "id": 2,
      "name": "Deposit (3% Rate)",
      "data": [35250, 38070, 39480, 40890, 38070, 49350, 56400]
    },
    {
      "id": 3,
      "name": "Pending credit",
      "data": [41300, 28910, 16520, 28910, 24800]
    }
  ]
}
